ffbot/__init__.py
ffbot/constants.py
ffbot/optimizer.py
ffbot/scraper.py
ffbot/utils.py
ffbot-1.2.11.dist-info/LICENSE
ffbot-1.2.11.dist-info/METADATA
ffbot-1.2.11.dist-info/WHEEL
ffbot-1.2.11.dist-info/top_level.txt
ffbot-1.2.11.dist-info/RECORD
