Metadata-Version: 2.1
Name: ffbot
Version: 1.2.11
Summary: Automate playing Yahoo Fantasy Football
Home-page: https://github.com/amarvin/fantasy-football-bot
Author: Alex Marvin
Author-email: alex.marvin@gmail.com
Keywords: fantasy-football bot yahoo
Classifier: Development Status :: 5 - Production/Stable
Classifier: License :: OSI Approved :: MIT License
Classifier: Programming Language :: Python :: 3
Requires-Python: >=3.0
License-File: LICENSE
Requires-Dist: beautifulsoup4
Requires-Dist: loguru
Requires-Dist: lxml
Requires-Dist: pandas
Requires-Dist: pulp
Requires-Dist: requests
Requires-Dist: tqdm
Requires-Dist: user-agent
